make_room/__init__.py
make_room/make_room.py
make_room/to_avif.py
make_room-0.0.1.dist-info/METADATA
make_room-0.0.1.dist-info/WHEEL
make_room-0.0.1.dist-info/entry_points.txt
make_room-0.0.1.dist-info/RECORD
